B2_lightTraffic/Decoder_led7seg_anode.v
//==========================================================================================================================
// File Name: Decoder_led7seg_anode.v
// Project Name: Thiet ke mach den giao thong co hien thi thoi gian.
// Author: Le Chi Huy - 24119134 - nganh Cong Nghe Ky thuat may tinh - Truong Dai hoc Cong Nghe Ky Thuat TP.HCM
// Date: 09 - 04 - 2026
// Version: 1.0
// Description: Bo giai ma cho led 7 doan anode chung.
//              Dau vao: timer (gia tri tu 0 den 9 de hien thi tren led 7 doan)
//              Dau ra: Q (tin hieu dieu khien cho led 7 doan, 0 la sang, 1 la tat)
//==========================================================================================================================

`timescale 1s/1ms

module Decoder_Led7Seg_Anode (
//------------------- Thoi gian --------------------//
    input wire [4:0] timer, // Thoi gian tu 0 den 9 de hien thi tren led 7 doan

//------------------- switch --------------------//
    input wire sw, // sw = 0: Trang thai binh thuong, sw = 1: trang thai den nhap nhay

//------------------- Ngo ra --------------------//
    output reg [6:0] Q // Tin hieu dieu khien cho led 7 doan, 0 la sang, 1 la tat
);

//---------------------------------------------------------------//
// 1. GIAI MA THOI GIAN TU 0 DEN 9 THANH TIN HIEU CHO LED 7 DOAN ANODE
//---------------------------------------------------------------//
always @(*) begin
    if(sw) begin
        Q = 7'b1111111; // Tat tat ca khi o trang thai nhap nhay den vang
    end
    else begin
    case(timer)
       'd0: Q = 7'b0000001; // (a,b,c,d,e,f: sang; g: tat)
       'd1: Q = 7'b1001111; // (b,c: sang; a,d,e,f,g tat)
       'd2: Q = 7'b0010010; // (a,b,d,e,g: sang; c,f: tat)
       'd3: Q = 7'b0000110; // (a,b,c,d,g: sang; e,f: tat)
       'd4: Q = 7'b1001000; // (b,c,f,g: sang; a,d,e: tat)
       'd5: Q = 7'b0100100; // (a,c,d,f,g: sang; b,e: tat)
       'd6: Q = 7'b0100000; // (a,c,d,e,f,g: sang; b: tat)
       'd7: Q = 7'b0001111; // (a,b,c: sang; d,e,f,g: tat)
       'd8: Q = 7'b0000000; // (a,b,c,d,e,f,g: sang; h: tat)
       'd9: Q = 7'b0000100; // (a,b,c,d,f,g: sang; e: tat)
       default: Q = 7'b1111111; // Tat tat ca khi o trang thai nhap nhay den vang
    endcase
    end
    
end
endmodule

B2_lightTraffic/LightTraffic_fsm.v
//==========================================================================================================================
// File Name: LightTraffic_fsm.v
// Project Name: Thiet ke mach den giao thong co hien thi thoi gian.
// Author: Le Chi Huy - 24119134 - nganh Cong Nghe Ky thuat may tinh - Truong Dai hoc Cong Nghe Ky Thuat TP.HCM
// Date: 09 - 04 - 2026
// Version: 1.0
// Description: Su dung mo hinh may trang thai huu han (FSM) de dieu khien den giao thong tai cac nga tu.
//              Ho tro che do binh thuong va che do nhap nhay vang (sw).
//              Tan so xung clock ngo vao la 1Hz.
//              Thoi gian moi cot se duoc hien thi tren 2 led 7 doan anode chung duoc ket noi truc tiep voi IO cua FPGA.
//==========================================================================================================================

`timescale 1s/1ms
module LightTraffic_fsm (
    //------- Clock -------//
    input wire clk, // Xung nhip cho he thong, tan so 1Hz

    //-------tin hieu dieu khien -------//
    input wire sw, // sw = 0: Trang thai binh thuong, sw = 1: trang thai den nhap nhay

    //------- Ngo ra -------//
    output reg [5:0] Q, // Tin hieu dieu khien den giao thong: Q[5:3] cho cot den 1(xanh, vang, do), Q[2:0] cho cot den 2(xanh, vang, do)
    output wire [6:0] led7seg_Chuc1,  // Du lieu cho led 7 doan hien thi hang chuc cua cot den 1
    output wire [6:0] led7seg_DonVi1, // Du lieu cho led 7 doan hien thi hang don vi cua cot den 1
    output wire [6:0] led7seg_Chuc2,  // Du lieu cho led 7 doan hien thi hang chuc cua cot den 2
    output wire [6:0] led7seg_DonVi2  // Du lieu cho led 7 doan hien thi hang don vi cua cot den 2
);

parameter [2:0] S1 = 3'b000, S2 = 3'b001, S3 = 3'b010, S4 = 3'b011; // Trang thai hoat dong binh thuong cua den giao thong
parameter [2:0] S5 = 3'b100, S6 = 3'b101; // Trang thai nhap nhay den vang

parameter Time_R = 15, Time_G = 15, Time_Y = 5, Time_YR = 5, Time_Blink = 1; // Thoi gian cho moi trang thai (don vi: giay)

parameter [5:0] l1 = 6'b100_001, l2 = 6'b010_001, l3 = 6'b001_010, l4 = 6'b001_100; // Cac trang thai ngo ra cho den giao thong
//l1: Cot 1 xanh, cot 2 do; l2: Cot 1 vang, cot 2 do; l3: Cot 1 do, cot 2 xanh; l4: Cot 1 do, cot 2 vang

parameter [5:0] BlinkLight = 6'b010_010; // Trang thai ngo ra o che do nhap nhay vang: ca hai cot deu bat den vang

reg [3:0] timer; // Bo dem thoi gian de thay doi trang thai den giao thong. Dem nguoc tu trang thai thoi hien tai ve 0, sau do chuyen trang thai tiep theo
reg [4:0] TRL1, TRL2; // Bo dem thoi gian cho moi cot den giao thong, giup hien thi thoi gian con lai tren Led 7 doan
reg [4:0] DonVi1, Chuc1, Chuc2, DonVi2; // Tach cac gia tri thoi gian con lai thanh hang don vi va hang chuc de hien thi tren Led 7 doan cua moi cot
reg [2:0] CurrentTime, NextTime; // Doc trang thai hien tai va tim kiem trang thai tiep theo dua vao trang thai hien tai

//------------Khoi tao nhung trang thai ban dau ------------//
initial begin
    CurrentTime = (sw) ? S5 : S1; // Xac nhan trang thai ban dau dua tren tin hieu dieu khien sw
    timer = Time_G; // Hien thi den xanh o cot 1 va den do o cot 2 khi bat dau
    TRL1 = Time_G; // Hien thi thoi gian dem nguoc cho den xanh o cot 1 khi bat dau
    TRL2 = Time_R + Time_Y; // Hien thi tong thoi gian dem nguoc cho den do o cot 2 khi bat dau (bao gom ca thoi gian den do o cot 2 va thoi gian den vang o cot 1)
end
//---------------------------------------------------------//

//----------------------------------------------------------------------------------------//
// 1. XAC DINH TRANG THAI HIEN TAI & TRANG THAI DEM NGUOC & THOI GIAN CHO MOI TRANG THAI //
//--------------------------------------------------------------------------------------//
always @(posedge clk or posedge sw) begin
    TRL1 <= TRL1 - 1; // Dem nguoc thoi gian hien thi tren led 7 doan cho cot den 1
    TRL2 <= TRL2 - 1; // Dem nguoc thoi gian hien thi tren led 7 doan cho cot den 2

    if(sw && CurrentTime != S5 && CurrentTime != S6) begin // Neu sw = 1, he thong chuyen sang che do nhap nhay vang, thoi gian dem nguoc cho ca hai cot den deu la Time_Blink
        timer <= Time_Blink;
        CurrentTime = S5; // Trang thai thoi gian hien tai la ca hai cot den deu bat den vang
        NextTime = S6; // Trang thai thoi gian tiep theo la ca hai c
    end
    else begin 
        if(timer > 1) begin  //  Dem nguoc thoi gian cho trang thai thoi gian hien tai
            timer <= timer - 1; 
        end

        else begin  // Xac dinh trang thai thoi gian hien tai sau khi cap nhat trang thai tiep theo
            CurrentTime = NextTime;
            case( CurrentTime)  // Xac dinh trang thai thoi gian hien tai va cap nhat thoi gian dem nguoc cho moi cot den giao thong tuong ung
                S1: begin // Trang thai 1: Cot 1 xanh, cot 2 do
                    timer <= Time_G;
                    TRL1 <= Time_G; // Hien thi thoi gian dem nguoc cho den xanh o cot 1 khi cot 2 bat den do
                    TRL2 <= Time_R + Time_Y; // Hien thi tong thoi gian dem nguoc cho den do o cot 2 khi cot 1 bat den xanh (bao gom ca thoi gian den do o cot 2 va thoi gian den vang o cot 1)
                end

                S2: begin // Trang thai 2: Cot 1 vang, cot 2 do
                    timer <= Time_Y;
                    TRL1 <= Time_Y; // Hien thi thoi gian dem nguoc cho den vang o cot 1 khi cot 2 van bat den do
                end

                S3: begin // Trang thai 3: Cot 1 do, cot 2 xanh
                    timer <= Time_YR;
                    TRL1 <= Time_YR + Time_R; // Hien thi tong thoi gian dem nguoc cho den do o cot 1 khi cot 1 bat den do (bao gom ca thoi gian den do o cot 1 va thoi gian den vang o cot 2)
                    TRL2 <= Time_YR; // Hien thi thoi gian dem nguoc cho den vang o cot 2 khi cot 1 bat den do
                end

                S4: begin  // Trang thai 4: Cot 1 do, cot 2 vang
                    timer <= Time_R;
                    TRL2 <= Time_G; // Hien thi thoi gian dem nguoc cho den xanh o cot 2 khi cot 1 bat den do
                end

                S5: begin // Trang thai 5: Ca hai cot den deu nhap nhay vang
                    timer <= Time_Blink; 
                    TRL1 <= 0; // Khong hien thi thoi gian dem nguoc cho cot den 1 trong che do nhap nhay vang
                    TRL2 <= 0; // Khong hien thi thoi gian dem nguoc cho cot den 2 trong che do nhap nhay vang
                end

                S6: begin // Trang thai 6: Ca hai cot den deu tat (trong che do nhap nhay vang)
                    timer <= Time_Blink;    
                    TRL1 <= 0; // Khong hien thi thoi gian dem nguoc cho cot den 1 trong che do nhap nhay vang
                    TRL2 <= 0; // Khong hien thi thoi gian dem nguoc cho cot den 2 trong che do nhap nhay vang
                end

                default: begin // Trang thai mac dinh: Cot 1 xanh, cot 2 do
                    timer <= Time_G;
                    TRL1 <= Time_G; // Hien thi thoi gian dem nguoc cho den xanh o cot 1 khi cot 2 bat den do
                    TRL2 <= Time_R + Time_Y; // Hien thi tong thoi gian dem nguoc cho den do o cot 2 khi cot 1 bat den xanh (bao gom ca thoi gian den do o cot 2 va thoi gian den vang o cot 1)
                end
            endcase
        end
    end
end

//----------------------------------------------------------------------------------------//
// 2. XAC DINH TRANG THAI TIEP
//----------------------------------------------------------------------------------------//
always @(*) begin

        if(sw) begin // He thong chuyen sang che do nhap nhay vang khi sw = 1
            case(CurrentTime) // Xac dinh trang thai thoi gian tiep theo trong che do nhap nhay vang
                S5: NextTime = S6; // Trang thai thoi gian tiep theo sau khi ca hai cot den deu bat den vang la ca hai cot den deu tat
                S6: NextTime = S5; // Trang thai thoi gian tiep theo sau khi ca hai cot den deu tat la ca hai cot den deu bat den vang
                default: NextTime = S5; // Trang thai thoi gian mac dinh cua ca hai cot den deu bat den vang
            endcase
        end
        else begin // He thong chuyen sang che do hoat dong binh thuong khi sw = 0
         case(CurrentTime) // Xac dinh trang thai thoi gian tiep theo (theo chu trinh S1 -> S2 -> S3 -> S4 -> S1)
            S1: NextTime = S2; // Trang thai thoi gian tiep theo la cot 1 vang, cot 2 do
            S2: NextTime = S3; // Trang thai thoi gian tiep theo la cot 1 do, cot 2 xanh
            S3: NextTime = S4; // Trang thai thoi gian tiep theo la cot 1 do, cot 2 vang
            S4: NextTime = S1; // Trang thai thoi gian tiep theo la cot 1 xanh, cot 2 do
            default: NextTime = S1; // Trang thai thoi gian mac dinh la cot 1 xanh, cot 2 do
         endcase
    end
end

//----------------------------------------------------------------------------------------//
// 3. HIEN THI THOI GIAN CON LAI TREN LED 7 DOAN & XAC DINH NGO RA CHO DEN GIAO THONG
//----------------------------------------------------------------------------------------//
always @(*) begin
    DonVi1 = TRL1 % 10; // Hien thi hang don vi cho cot den 1 tren led 7 doan
    Chuc1  = TRL1 / 10; // Hien thi hang chuc cot den 1 tren led 7 doan
    DonVi2 = TRL2 % 10; // Hien thi hang don vi cho cot den 2 tren led 7 doan
    Chuc2  = TRL2 / 10; // Hien thi hang chuc cho cot den 2 tren led 7 doan

end
//------------------Module giai ma Led 7 doan anode cho moi cot den giao thong------------------//
Decoder_Led7Seg_Anode DV1(.timer(DonVi1), .Q(led7seg_DonVi1), .sw(sw)); // Giai ma hang don vi cho cot den 1
Decoder_Led7Seg_Anode C1(.timer(Chuc1), .Q(led7seg_Chuc1), .sw(sw)); // Giai ma hang chuc cho cot den 1
Decoder_Led7Seg_Anode DV2(.timer(DonVi2), .Q(led7seg_DonVi2), .sw(sw)); // Giai ma hang don vi cho cot den 2
Decoder_Led7Seg_Anode C2(.timer(Chuc2), .Q(led7seg_Chuc2), .sw(sw)); // Giai ma hang chuc cho cot den 2
//---------------------------------------------------------------------------------------------//

always @(*) begin
    case(CurrentTime) // Xac dinh ngo ra cho den giao thong dua tren trang thai thoi gian hien tai
        S1:  Q = l1;  // Trang thai 1: Cot 1 xanh, cot 2 do
        S2:  Q = l2;  // Trang thai 2: Cot 1 vang, cot 2 do
        S3:  Q = l3;  // Trang thai 3: Cot 1 do, cot 2 xanh
        S4:  Q = l4;  // Trang thai 4: Cot 1 do, cot 2 vang
        S5:  Q = BlinkLight;  // Trang thai 5: Ca hai cot den deu nhap nhay vang
        S6:  Q = 6'b000_000; // Trang thai 6: Ca hai cot den deu tat (trong che do nhap nhay vang)
        default: Q = l1;  // Trang thai ngo ra mac dinh: Cot 1 xanh, cot 2 do
    endcase
end     

endmodule

B2_lightTraffic/tb_LightTraffic.v
`timescale 1s/1ms
module tb_LightTraffic;

wire [5:0] Q;
wire [6:0] led7seg_DonVi1, led7seg_Chuc1, led7seg_DonVi2, led7seg_Chuc2;
reg clk, sw;
LightTraffic_fsm uut(
    .clk(clk), 
    .Q(Q), 
    .sw(sw),
    .led7seg_DonVi1(led7seg_DonVi1), 
    .led7seg_Chuc1(led7seg_Chuc1),
    .led7seg_DonVi2(led7seg_DonVi2), 
    .led7seg_Chuc2(led7seg_Chuc2)
    );

initial begin
    clk =0;
    forever #0.5 clk = ~clk;
end

initial begin
    sw = 0;
    #50 sw = 1; // Activate blinking mode
    #15 $finish;
end

initial begin
    $monitor("sw = %1b ||| Time = %2d |  Den Q = %6b |Chuc 1: %7b | Don Vi 1: %7b | Chuc 2: %7b | Don Vi 1: %7b", uut.sw, uut.timer, Q, led7seg_Chuc1, led7seg_DonVi1, led7seg_Chuc2, led7seg_DonVi2);
end

initial begin
    $dumpfile("wave.vcd");
    $dumpvars(0,tb_LightTraffic);
end

endmodule

B2_lightTraffic/wave.vcd
$date
	Wed Apr  8 19:54:02 2026
$end
$version
	Icarus Verilog
$end
$timescale
	1ms
$end
$scope module tb_LightTraffic $end
$var wire 7 ! led7seg_DonVi2 [6:0] $end
$var wire 7 " led7seg_DonVi1 [6:0] $end
$var wire 7 # led7seg_Chuc2 [6:0] $end
$var wire 7 $ led7seg_Chuc1 [6:0] $end
$var wire 6 % Q [5:0] $end
$var reg 1 & clk $end
$var reg 1 ' sw $end
$scope module uut $end
$var wire 1 & clk $end
$var wire 1 ' sw $end
$var wire 7 ( led7seg_DonVi2 [6:0] $end
$var wire 7 ) led7seg_DonVi1 [6:0] $end
$var wire 7 * led7seg_Chuc2 [6:0] $end
$var wire 7 + led7seg_Chuc1 [6:0] $end
$var parameter 6 , BlinkLight $end
$var parameter 3 - S1 $end
$var parameter 3 . S2 $end
$var parameter 3 / S3 $end
$var parameter 3 0 S4 $end
$var parameter 3 1 S5 $end
$var parameter 3 2 S6 $end
$var parameter 32 3 Time_Blink $end
$var parameter 32 4 Time_G $end
$var parameter 32 5 Time_R $end
$var parameter 32 6 Time_Y $end
$var parameter 32 7 Time_YR $end
$var parameter 6 8 l1 $end
$var parameter 6 9 l2 $end
$var parameter 6 : l3 $end
$var parameter 6 ; l4 $end
$var reg 5 < Chuc1 [4:0] $end
$var reg 5 = Chuc2 [4:0] $end
$var reg 3 > CurrentTime [2:0] $end
$var reg 5 ? DonVi1 [4:0] $end
$var reg 5 @ DonVi2 [4:0] $end
$var reg 3 A NextTime [2:0] $end
$var reg 6 B Q [5:0] $end
$var reg 5 C TRL1 [4:0] $end
$var reg 5 D TRL2 [4:0] $end
$var reg 4 E timer [3:0] $end
$scope module C1 $end
$var wire 1 ' sw $end
$var wire 5 F timer [4:0] $end
$var reg 7 G Q [6:0] $end
$upscope $end
$scope module C2 $end
$var wire 1 ' sw $end
$var wire 5 H timer [4:0] $end
$var reg 7 I Q [6:0] $end
$upscope $end
$scope module DV1 $end
$var wire 1 ' sw $end
$var wire 5 J timer [4:0] $end
$var reg 7 K Q [6:0] $end
$upscope $end
$scope module DV2 $end
$var wire 1 ' sw $end
$var wire 5 L timer [4:0] $end
$var reg 7 M Q [6:0] $end
$upscope $end
$upscope $end
$upscope $end
$enddefinitions $end
$comment Show the parameter values. $end
$dumpall
b1100 ;
b1010 :
b10001 9
b100001 8
b101 7
b101 6
b1111 5
b1111 4
b1 3
b101 2
b100 1
b11 0
b10 /
b1 .
b0 -
b10010 ,
$end
#0
$dumpvars
b1 M
b0 L
b100100 K
b101 J
b10010 I
b10 H
b1001111 G
b1 F
b1111 E
b10100 D
b1111 C
b100001 B
b0 A
b0 @
b101 ?
bx00 >
b10 =
b1 <
b1001111 +
b10010 *
b100100 )
b1 (
0'
0&
b100001 %
b1001111 $
b10010 #
b100100 "
b1 !
$end
#500
b1001111 #
b1001111 *
b1001111 I
b100 !
b100 (
b100 M
b1001000 "
b1001000 )
b1001000 K
b1 =
b1 H
b1001 @
b1001 L
b100 ?
b100 J
b1110 E
b10011 D
b1110 C
1&
#1000
0&
#1500
b0 !
b0 (
b0 M
b110 "
b110 )
b110 K
b1000 @
b1000 L
b11 ?
b11 J
b1101 E
b10010 D
b1101 C
1&
#2000
0&
#2500
b1111 !
b1111 (
b1111 M
b10010 "
b10010 )
b10010 K
b111 @
b111 L
b10 ?
b10 J
b1100 E
b10001 D
b1100 C
1&
#3000
0&
#3500
b100000 !
b100000 (
b100000 M
b1001111 "
b1001111 )
b1001111 K
b110 @
b110 L
b1 ?
b1 J
b1011 E
b10000 D
b1011 C
1&
#4000
0&
#4500
b100100 !
b100100 (
b100100 M
b1 "
b1 )
b1 K
b101 @
b101 L
b0 ?
b0 J
b1010 E
b1111 D
b1010 C
1&
#5000
0&
#5500
b1001000 !
b1001000 (
b1001000 M
b1 $
b1 +
b1 G
b100 "
b100 )
b100 K
b100 @
b100 L
b0 <
b0 F
b1001 ?
b1001 J
b1001 E
b1110 D
b1001 C
1&
#6000
0&
#6500
b110 !
b110 (
b110 M
b0 "
b0 )
b0 K
b11 @
b11 L
b1000 ?
b1000 J
b1000 E
b1101 D
b1000 C
1&
#7000
0&
#7500
b10010 !
b10010 (
b10010 M
b1111 "
b1111 )
b1111 K
b10 @
b10 L
b111 ?
b111 J
b111 E
b1100 D
b111 C
1&
#8000
0&
#8500
b1001111 !
b1001111 (
b1001111 M
b100000 "
b100000 )
b100000 K
b1 @
b1 L
b110 ?
b110 J
b110 E
b1011 D
b110 C
1&
#9000
0&
#9500
b1 !
b1 (
b1 M
b100100 "
b100100 )
b100100 K
b0 @
b0 L
b101 ?
b101 J
b101 E
b1010 D
b101 C
1&
#10000
0&
#10500
b1 #
b1 *
b1 I
b100 !
b100 (
b100 M
b1001000 "
b1001000 )
b1001000 K
b0 =
b0 H
b1001 @
b1001 L
b100 ?
b100 J
b100 E
b1001 D
b100 C
1&
#11000
0&
#11500
b0 !
b0 (
b0 M
b110 "
b110 )
b110 K
b1000 @
b1000 L
b11 ?
b11 J
b11 E
b1000 D
b11 C
1&
#12000
0&
#12500
b1111 !
b1111 (
b1111 M
b10010 "
b10010 )
b10010 K
b111 @
b111 L
b10 ?
b10 J
b10 E
b111 D
b10 C
1&
#13000
0&
#13500
b100000 !
b100000 (
b100000 M
b1001111 "
b1001111 )
b1001111 K
b110 @
b110 L
b1 ?
b1 J
b1 E
b110 D
b1 C
1&
#14000
0&
#14500
b10010 #
b10010 *
b10010 I
b1 !
b1 (
b1 M
b1001111 $
b1001111 +
b1001111 G
b100100 "
b100100 )
b100100 K
b10 =
b10 H
b0 @
b0 L
b1 <
b1 F
b101 ?
b101 J
b1111 E
b10100 D
b1111 C
b1 A
b0 >
1&
#15000
0&
#15500
b1001111 #
b1001111 *
b1001111 I
b100 !
b100 (
b100 M
b1001000 "
b1001000 )
b1001000 K
b1 =
b1 H
b1001 @
b1001 L
b100 ?
b100 J
b1110 E
b10011 D
b1110 C
1&
#16000
0&
#16500
b0 !
b0 (
b0 M
b110 "
b110 )
b110 K
b1000 @
b1000 L
b11 ?
b11 J
b1101 E
b10010 D
b1101 C
1&
#17000
0&
#17500
b1111 !
b1111 (
b1111 M
b10010 "
b10010 )
b10010 K
b111 @
b111 L
b10 ?
b10 J
b1100 E
b10001 D
b1100 C
1&
#18000
0&
#18500
b100000 !
b100000 (
b100000 M
b1001111 "
b1001111 )
b1001111 K
b110 @
b110 L
b1 ?
b1 J
b1011 E
b10000 D
b1011 C
1&
#19000
0&
#19500
b100100 !
b100100 (
b100100 M
b1 "
b1 )
b1 K
b101 @
b101 L
b0 ?
b0 J
b1010 E
b1111 D
b1010 C
1&
#20000
0&
#20500
b1001000 !
b1001000 (
b1001000 M
b1 $
b1 +
b1 G
b100 "
b100 )
b100 K
b100 @
b100 L
b0 <
b0 F
b1001 ?
b1001 J
b1001 E
b1110 D
b1001 C
1&
#21000
0&
#21500
b110 !
b110 (
b110 M
b0 "
b0 )
b0 K
b11 @
b11 L
b1000 ?
b1000 J
b1000 E
b1101 D
b1000 C
1&
#22000
0&
#22500
b10010 !
b10010 (
b10010 M
b1111 "
b1111 )
b1111 K
b10 @
b10 L
b111 ?
b111 J
b111 E
b1100 D
b111 C
1&
#23000
0&
#23500
b1001111 !
b1001111 (
b1001111 M
b100000 "
b100000 )
b100000 K
b1 @
b1 L
b110 ?
b110 J
b110 E
b1011 D
b110 C
1&
#24000
0&
#24500
b1 !
b1 (
b1 M
b100100 "
b100100 )
b100100 K
b0 @
b0 L
b101 ?
b101 J
b101 E
b1010 D
b101 C
1&
#25000
0&
#25500
b1 #
b1 *
b1 I
b100 !
b100 (
b100 M
b1001000 "
b1001000 )
b1001000 K
b0 =
b0 H
b1001 @
b1001 L
b100 ?
b100 J
b100 E
b1001 D
b100 C
1&
#26000
0&
#26500
b0 !
b0 (
b0 M
b110 "
b110 )
b110 K
b1000 @
b1000 L
b11 ?
b11 J
b11 E
b1000 D
b11 C
1&
#27000
0&
#27500
b1111 !
b1111 (
b1111 M
b10010 "
b10010 )
b10010 K
b111 @
b111 L
b10 ?
b10 J
b10 E
b111 D
b10 C
1&
#28000
0&
#28500
b100000 !
b100000 (
b100000 M
b1001111 "
b1001111 )
b1001111 K
b110 @
b110 L
b1 ?
b1 J
b1 E
b110 D
b1 C
1&
#29000
0&
#29500
b100100 !
b100100 (
b100100 M
b100100 "
b100100 )
b100100 K
b101 @
b101 L
b101 ?
b101 J
b101 E
b101 D
b101 C
b10001 %
b10001 B
b10 A
b1 >
1&
#30000
0&
#30500
b1001000 !
b1001000 (
b1001000 M
b1001000 "
b1001000 )
b1001000 K
b100 @
b100 L
b100 ?
b100 J
b100 E
b100 D
b100 C
1&
#31000
0&
#31500
b110 !
b110 (
b110 M
b110 "
b110 )
b110 K
b11 @
b11 L
b11 ?
b11 J
b11 E
b11 D
b11 C
1&
#32000
0&
#32500
b10010 !
b10010 (
b10010 M
b10010 "
b10010 )
b10010 K
b10 @
b10 L
b10 ?
b10 J
b10 E
b10 D
b10 C
1&
#33000
0&
#33500
b1001111 !
b1001111 (
b1001111 M
b1001111 "
b1001111 )
b1001111 K
b1 @
b1 L
b1 ?
b1 J
b1 E
b1 D
b1 C
1&
#34000
0&
#34500
b100100 !
b100100 (
b100100 M
b10010 $
b10010 +
b10010 G
b1 "
b1 )
b1 K
b101 @
b101 L
b10 <
b10 F
b0 ?
b0 J
b101 E
b101 D
b10100 C
b1010 %
b1010 B
b11 A
b10 >
1&
#35000
0&
#35500
b1001000 !
b1001000 (
b1001000 M
b1001111 $
b1001111 +
b1001111 G
b100 "
b100 )
b100 K
b100 @
b100 L
b1 <
b1 F
b1001 ?
b1001 J
b100 E
b100 D
b10011 C
1&
#36000
0&
#36500
b110 !
b110 (
b110 M
b0 "
b0 )
b0 K
b11 @
b11 L
b1000 ?
b1000 J
b11 E
b11 D
b10010 C
1&
#37000
0&
#37500
b10010 !
b10010 (
b10010 M
b1111 "
b1111 )
b1111 K
b10 @
b10 L
b111 ?
b111 J
b10 E
b10 D
b10001 C
1&
#38000
0&
#38500
b1001111 !
b1001111 (
b1001111 M
b100000 "
b100000 )
b100000 K
b1 @
b1 L
b110 ?
b110 J
b1 E
b1 D
b10000 C
1&
#39000
0&
#39500
b1001111 #
b1001111 *
b1001111 I
b100100 !
b100100 (
b100100 M
b100100 "
b100100 )
b100100 K
b1 =
b1 H
b101 @
b101 L
b101 ?
b101 J
b1111 E
b1111 D
b1111 C
b1100 %
b1100 B
b0 A
b11 >
1&
#40000
0&
#40500
b1001000 !
b1001000 (
b1001000 M
b1001000 "
b1001000 )
b1001000 K
b100 @
b100 L
b100 ?
b100 J
b1110 E
b1110 D
b1110 C
1&
#41000
0&
#41500
b110 !
b110 (
b110 M
b110 "
b110 )
b110 K
b11 @
b11 L
b11 ?
b11 J
b1101 E
b1101 D
b1101 C
1&
#42000
0&
#42500
b10010 !
b10010 (
b10010 M
b10010 "
b10010 )
b10010 K
b10 @
b10 L
b10 ?
b10 J
b1100 E
b1100 D
b1100 C
1&
#43000
0&
#43500
b1001111 !
b1001111 (
b1001111 M
b1001111 "
b1001111 )
b1001111 K
b1 @
b1 L
b1 ?
b1 J
b1011 E
b1011 D
b1011 C
1&
#44000
0&
#44500
b1 !
b1 (
b1 M
b1 "
b1 )
b1 K
b0 @
b0 L
b0 ?
b0 J
b1010 E
b1010 D
b1010 C
1&
#45000
0&
#45500
b1 #
b1 *
b1 I
b100 !
b100 (
b100 M
b1 $
b1 +
b1 G
b100 "
b100 )
b100 K
b0 =
b0 H
b1001 @
b1001 L
b0 <
b0 F
b1001 ?
b1001 J
b1001 E
b1001 D
b1001 C
1&
#46000
0&
#46500
b0 !
b0 (
b0 M
b0 "
b0 )
b0 K
b1000 @
b1000 L
b1000 ?
b1000 J
b1000 E
b1000 D
b1000 C
1&
#47000
0&
#47500
b1111 !
b1111 (
b1111 M
b1111 "
b1111 )
b1111 K
b111 @
b111 L
b111 ?
b111 J
b111 E
b111 D
b111 C
1&
#48000
0&
#48500
b100000 !
b100000 (
b100000 M
b100000 "
b100000 )
b100000 K
b110 @
b110 L
b110 ?
b110 J
b110 E
b110 D
b110 C
1&
#49000
0&
#49500
b100100 !
b100100 (
b100100 M
b100100 "
b100100 )
b100100 K
b101 @
b101 L
b101 ?
b101 J
b101 E
b101 D
b101 C
1&
#50000
b100 @
b100 L
b100 ?
b100 J
b1 E
b100 D
b100 C
b10010 %
b10010 B
b1111111 $
b1111111 +
b1111111 G
b1111111 #
b1111111 *
b1111111 I
b1111111 "
b1111111 )
b1111111 K
b1111111 !
b1111111 (
b1111111 M
b100 >
b101 A
0&
1'
#50500
b0 @
b0 L
b0 ?
b0 J
b0 D
b0 C
b0 %
b0 B
b100 A
b101 >
1&
#51000
0&
#51500
b0 D
b0 C
b10010 %
b10010 B
b101 A
b100 >
1&
#52000
0&
#52500
b0 D
b0 C
b0 %
b0 B
b100 A
b101 >
1&
#53000
0&
#53500
b0 D
b0 C
b10010 %
b10010 B
b101 A
b100 >
1&
#54000
0&
#54500
b0 D
b0 C
b0 %
b0 B
b100 A
b101 >
1&
#55000
0&
#55500
b0 D
b0 C
b10010 %
b10010 B
b101 A
b100 >
1&
#56000
0&
#56500
b0 D
b0 C
b0 %
b0 B
b100 A
b101 >
1&
#57000
0&
#57500
b0 D
b0 C
b10010 %
b10010 B
b101 A
b100 >
1&
#58000
0&
#58500
b0 D
b0 C
b0 %
b0 B
b100 A
b101 >
1&
#59000
0&
#59500
b0 D
b0 C
b10010 %
b10010 B
b101 A
b100 >
1&
#60000
0&
#60500
b0 D
b0 C
b0 %
b0 B
b100 A
b101 >
1&
#61000
0&
#61500
b0 D
b0 C
b10010 %
b10010 B
b101 A
b100 >
1&
#62000
0&
#62500
b0 D
b0 C
b0 %
b0 B
b100 A
b101 >
1&
#63000
0&
#63500
b0 D
b0 C
b10010 %
b10010 B
b101 A
b100 >
1&
#64000
0&
#64500
b0 D
b0 C
b0 %
b0 B
b100 A
b101 >
1&
